coco/__init__.py
coco/coco.json
coco/coco.py
coco/database.json
coco/prompt.py
coco_cli-2.3.dist-info/LICENSE
coco_cli-2.3.dist-info/METADATA
coco_cli-2.3.dist-info/WHEEL
coco_cli-2.3.dist-info/entry_points.txt
coco_cli-2.3.dist-info/top_level.txt
coco_cli-2.3.dist-info/RECORD
